aiokeitaro/__init__.py
aiokeitaro/api.py
aiokeitaro/keitaro.py
aiokeitaro/utils.py
aiokeitaro/resources/__init__.py
aiokeitaro/resources/affiliate_networks.py
aiokeitaro/resources/botlist.py
aiokeitaro/resources/campaigns.py
aiokeitaro/resources/clicks.py
aiokeitaro/resources/domains.py
aiokeitaro/resources/groups.py
aiokeitaro/resources/integrations.py
aiokeitaro/resources/landing_pages.py
aiokeitaro/resources/logs.py
aiokeitaro/resources/offers.py
aiokeitaro/resources/reports.py
aiokeitaro/resources/streams.py
aiokeitaro/resources/traffic_sources.py
aiokeitaro/resources/users.py
aiokeitaro-1.0.3.dist-info/LICENSE
aiokeitaro-1.0.3.dist-info/METADATA
aiokeitaro-1.0.3.dist-info/WHEEL
aiokeitaro-1.0.3.dist-info/top_level.txt
aiokeitaro-1.0.3.dist-info/RECORD
