Metadata-Version: 2.1
Name: aiokeitaro
Version: 1.0.3
Summary: Unofficial Asynchronous Keitaro Admin API client
Home-page: https://github.com/developerreva/aiokeitaro
Author: Developereva
Author-email: developereva@protonmail.com
Project-URL: Source Code, https://github.com/developerreva/aiokeitaro
Project-URL: Documentation, https://github.com/developerreva/aiokeitaro#-getting-started
Project-URL: Keitaro Admin API Documentation, https://admin-api.docs.keitaro.io/
Keywords: python python3 api-client aiohttp api-wrapper keitaro keitaro-tracker keitaro-async
Classifier: Programming Language :: Python :: 3
Classifier: License :: OSI Approved :: MIT License
Classifier: Operating System :: OS Independent
Requires-Python: >=3.6
License-File: LICENSE
Requires-Dist: aiohttp
